otp_generate/__init__.py
otp_generate/main.py
wa_otp_generate_project-0.0.1.dist-info/LICENSE
wa_otp_generate_project-0.0.1.dist-info/METADATA
wa_otp_generate_project-0.0.1.dist-info/WHEEL
wa_otp_generate_project-0.0.1.dist-info/top_level.txt
wa_otp_generate_project-0.0.1.dist-info/RECORD
